gravity_simulation/__init__.py
gravity_simulation/gravity.py
gravity_simulation/test.py
gravity_simulation-2.0.1.dist-info/LICENSE.txt
gravity_simulation-2.0.1.dist-info/METADATA
gravity_simulation-2.0.1.dist-info/WHEEL
gravity_simulation-2.0.1.dist-info/top_level.txt
gravity_simulation-2.0.1.dist-info/RECORD
