Metadata-Version: 2.1
Name: gravity-simulation
Version: 2.0.1
Summary: calculation and visualization of n-bodies gravity
Home-page: https://github.com/daodavid/gravity-simulation
Author-email: dstankov1993@gmail.com
License: MIT
Platform: UNKNOWN
Classifier: Programming Language :: Python :: 3
Classifier: License :: OSI Approved :: MIT License
Classifier: Operating System :: OS Independent
